{
  "project_info": {
    "project_number": "28140651852",
    "firebase_url": "https://speed-shopper-214314.firebaseio.com",
    "project_id": "speed-shopper-214314",
    "storage_bucket": "speed-shopper-214314.appspot.com"
  },
  "client": [
    {
      "client_info": {
        "mobilesdk_app_id": "1:28140651852:android:cee2f78f67a156e6",
        "android_client_info": {
          "package_name": "c.offerak.speedshopper"
        }
      },
      "oauth_client": [
        {
          "client_id": "28140651852-l1s9alaei3ueg9g96kqk1u34h9dq1kn6.apps.googleusercontent.com",
          "client_type": 1,
          "android_info": {
            "package_name": "c.offerak.speedshopper",
            "certificate_hash": "0a64e752ebe9094a15706bd08ba0cc37bf48378b"
          }
        },
        {
          "client_id": "28140651852-vajo3b9e69qslqjigag1305tfg02al83.apps.googleusercontent.com",
          "client_type": 3
        }
      ],
      "api_key": [
        {
          "current_key": "AIzaSyCEj0UH4-n78yEQob_dWy1jKeSVvFj5IBI"
        }
      ],
      "services": {
        "appinvite_service": {
          "other_platform_oauth_client": [
            {
              "client_id": "28140651852-vajo3b9e69qslqjigag1305tfg02al83.apps.googleusercontent.com",
              "client_type": 3
            },
            {
              "client_id": "28140651852-f4adfls8eelakkvsiesmc8gqnht33s9t.apps.googleusercontent.com",
              "client_type": 2,
              "ios_info": {
                "bundle_id": "com.speedshopper.app"
              }
            }
          ]
        }
      }
    }
  ],
  "configuration_version": "1"
}